fastapi_sse/__init__.py
fastapi_sse/backends.py
fastapi_sse/core.py
fastapi_sse/events.py
fastapi_sse/middleware.py
fastapi_sse/utils.py
fastapi_sse_wrapper-0.1.0.dist-info/licenses/LICENSE
fastapi_sse_wrapper-0.1.0.dist-info/METADATA
fastapi_sse_wrapper-0.1.0.dist-info/WHEEL
fastapi_sse_wrapper-0.1.0.dist-info/top_level.txt
fastapi_sse_wrapper-0.1.0.dist-info/RECORD
