Metadata-Version: 2.4
Name: fastapi-sse-wrapper
Version: 0.1.0
Summary: A small, production-minded SSE wrapper for FastAPI-based AI agents and chatbots.
Author-email: pratik <pratik@example.com>
License: MIT
Classifier: Programming Language :: Python :: 3.10
Classifier: License :: OSI Approved :: MIT License
Classifier: Framework :: FastAPI
Requires-Python: >=3.10
License-File: LICENSE
Requires-Dist: fastapi>=0.85.0
Requires-Dist: uvicorn>=0.20.0
Dynamic: license-file
